{"otherData": {},"traceEvents":[{"cat":"function","dur":65796,"name":"glfwInit","ph":"X","pid":0,"tid":240405105,"ts":104923108619},{"cat":"function","dur":694836,"name":"glfwCreateWindow","ph":"X","pid":0,"tid":240405105,"ts":104923174549},{"cat":"function","dur":3794,"name":"void __cdecl Calavera::OpenGLContext::Init(void)","ph":"X","pid":0,"tid":240405105,"ts":104923869513},{"cat":"function","dur":93,"name":"void __cdecl Calavera::WindowsWindow::SetVSync(bool)","ph":"X","pid":0,"tid":240405105,"ts":104923873441},{"cat":"function","dur":766063,"name":"void __cdecl Calavera::WindowsWindow::Init(const struct Calavera::WindowProps &)","ph":"X","pid":0,"tid":240405105,"ts":104923107518},{"cat":"function","dur":766103,"name":"__cdecl Calavera::WindowsWindow::WindowsWindow(const struct Calavera::WindowProps &)","ph":"X","pid":0,"tid":240405105,"ts":104923107517},{"cat":"function","dur":6,"name":"void __cdecl Calavera::OpenGLRendererAPI::Init(void)","ph":"X","pid":0,"tid":240405105,"ts":104923873688},{"cat":"function","dur":26,"name":"__cdecl Calavera::OpenGLVertexArray::OpenGLVertexArray(void)","ph":"X","pid":0,"tid":240405105,"ts":104923873744},{"cat":"function","dur":43,"name":"__cdecl Calavera::OpenGLVertexBuffer::OpenGLVertexBuffer(unsigned int)","ph":"X","pid":0,"tid":240405105,"ts":104923873832},{"cat":"function","dur":0,"name":"void __cdecl Calavera::OpenGLVertexBuffer::Bind(void) const","ph":"X","pid":0,"tid":240405105,"ts":104923873991},{"cat":"function","dur":91,"name":"void __cdecl Calavera::OpenGLVertexArray::AddVertexBuffer(const class std::shared_ptr<class Calavera::VertexBuffer> &)","ph":"X","pid":0,"tid":240405105,"ts":104923873946},{"cat":"function","dur":91,"name":"__cdecl Calavera::OpenGLIndexBuffer::OpenGLIndexBuffer(unsigned int *,unsigned int)","ph":"X","pid":0,"tid":240405105,"ts":104923874480},{"cat":"function","dur":0,"name":"void __cdecl Calavera::OpenGLIndexBuffer::Bind(void) const","ph":"X","pid":0,"tid":240405105,"ts":104923874611},{"cat":"function","dur":30,"name":"void __cdecl Calavera::OpenGLVertexArray::SetIndexBuffer(const class std::shared_ptr<class Calavera::IndexBuffer> &)","ph":"X","pid":0,"tid":240405105,"ts":104923874610},{"cat":"function","dur":534,"name":"__cdecl Calavera::OpenGLTexture2D::OpenGLTexture2D(unsigned int,unsigned int)","ph":"X","pid":0,"tid":240405105,"ts":104923874682},{"cat":"function","dur":7,"name":"void __cdecl Calavera::OpenGLTexture2D::SetData(void *,unsigned int)","ph":"X","pid":0,"tid":240405105,"ts":104923875279},{"cat":"function","dur":202,"name":"class std::basic_string<char,struct std::char_traits<char>,class std::allocator<char> > __cdecl Calavera::OpenGLShader::Readfile(const class std::basic_string<char,struct std::char_traits<char>,class std::allocator<char> > &)","ph":"X","pid":0,"tid":240405105,"ts":104923875330},{"cat":"function","dur":92,"name":"class std::unordered_map<unsigned int,class std::basic_string<char,struct std::char_traits<char>,class std::allocator<char> >,struct std::hash<unsigned int>,struct std::equal_to<unsigned int>,class std::allocator<struct std::pair<unsigned int const ,class std::basic_string<char,struct std::char_traits<char>,class std::allocator<char> > > > > __cdecl Calavera::OpenGLShader::PreProcess(const class std::basic_string<char,struct std::char_traits<char>,class std::allocator<char> > &)","ph":"X","pid":0,"tid":240405105,"ts":104923875580},{"cat":"function","dur":964,"name":"void __cdecl Calavera::OpenGLShader::Compile(const class std::unordered_map<unsigned int,class std::basic_string<char,struct std::char_traits<char>,class std::allocator<char> >,struct std::hash<unsigned int>,struct std::equal_to<unsigned int>,class std::allocator<struct std::pair<unsigned int const ,class std::basic_string<char,struct std::char_traits<char>,class std::allocator<char> > > > > &)","ph":"X","pid":0,"tid":240405105,"ts":104923875718},{"cat":"function","dur":1467,"name":"__cdecl Calavera::OpenGLShader::OpenGLShader(const class std::basic_string<char,struct std::char_traits<char>,class std::allocator<char> > &)","ph":"X","pid":0,"tid":240405105,"ts":104923875329},{"cat":"function","dur":4,"name":"void __cdecl Calavera::OpenGLShader::Bind(void) const","ph":"X","pid":0,"tid":240405105,"ts":104923876958},{"cat":"function","dur":47,"name":"void __cdecl Calavera::OpenGLShader::SetIntArray(const class std::basic_string<char,struct std::char_traits<char>,class std::allocator<char> > &,int *,unsigned int)","ph":"X","pid":0,"tid":240405105,"ts":104923877033},{"cat":"function","dur":3401,"name":"void __cdecl Calavera::Renderer2D::Init(void)","ph":"X","pid":0,"tid":240405105,"ts":104923873736},{"cat":"function","dur":3501,"name":"void __cdecl Calavera::Renderer::Init(void)","ph":"X","pid":0,"tid":240405105,"ts":104923873686},{"cat":"function","dur":7761,"name":"void __cdecl Calavera::ImGuiLayer::OnAttach(void)","ph":"X","pid":0,"tid":240405105,"ts":104923877235},{"cat":"function","dur":8092,"name":"void __cdecl Calavera::Application::PushOverlay(class Calavera::Layer *)","ph":"X","pid":0,"tid":240405105,"ts":104923877231},{"cat":"function","dur":777903,"name":"__cdecl Calavera::Application::Application(void)","ph":"X","pid":0,"tid":240405105,"ts":104923107507},{"cat":"function","dur":9,"name":"__cdecl Calavera::OrthographicCamera::OrthographicCamera(float,float,float,float)","ph":"X","pid":0,"tid":240405105,"ts":104923885487},{"cat":"function","dur":622,"name":"stbi_load - OpenGLTexture2D::OpenGLTexture2D(const std::string&)","ph":"X","pid":0,"tid":240405105,"ts":104923885576},{"cat":"function","dur":723,"name":"__cdecl Calavera::OpenGLTexture2D::OpenGLTexture2D(const class std::basic_string<char,struct std::char_traits<char>,class std::allocator<char> > &)","ph":"X","pid":0,"tid":240405105,"ts":104923885575},{"cat":"function","dur":768,"name":"void __cdecl Sandbox2D::OnAttach(void)","ph":"X","pid":0,"tid":240405105,"ts":104923885568},{"cat":"function","dur":813,"name":"void __cdecl Calavera::Application::PushLayer(class Calavera::Layer *)","ph":"X","pid":0,"tid":240405105,"ts":104923885552}]}